README.rst
setup.py
django_envconf.egg-info/PKG-INFO
django_envconf.egg-info/SOURCES.txt
django_envconf.egg-info/dependency_links.txt
django_envconf.egg-info/not-zip-safe
django_envconf.egg-info/requires.txt
django_envconf.egg-info/top_level.txt
envconf/__init__.py
envconf/envconf.py
envconf/path.py
envconf/test.py
envconf/schemas/__init__.py
envconf/schemas/django110.py