Metadata-Version: 1.1
Name: django-envconf
Version: 0.3.3
Summary: Django-envconf allows you to configure your application using environment variables as recommended by the 12factor methodology.
Home-page: https://github.com/achedeuzot/django-envconf
Author: Klemen Sever
Author-email: klemen@achedeuzot.me
License: BSD License
Download-URL: https://github.com/achedeuzot/django-envconf/tarball/0.3.3
Platform: UNKNOWN
Classifier: Development Status :: 5 - Production/Stable
Classifier: Environment :: Web Environment
Classifier: Framework :: Django
Classifier: Intended Audience :: Developers
Classifier: License :: OSI Approved :: BSD License
Classifier: Operating System :: OS Independent
Classifier: Programming Language :: Python
Classifier: Programming Language :: Python :: 2.7
Classifier: Programming Language :: Python :: 3
Classifier: Topic :: Internet :: WWW/HTTP
Classifier: Topic :: Internet :: WWW/HTTP :: Dynamic Content
